HISTORY.rst
LICENSE
MANIFEST.in
README.rst
setup.py
D2LValenceTUT.egg-info/PKG-INFO
D2LValenceTUT.egg-info/SOURCES.txt
D2LValenceTUT.egg-info/dependency_links.txt
D2LValenceTUT.egg-info/requires.txt
D2LValenceTUT.egg-info/top_level.txt
d2lvalence/__init__.py
d2lvalence/auth.py